{
    "os": "Linux-6.1.60-1-lts-x86_64-with-glibc2.38",
    "python": "3.11.5",
    "heartbeatAt": "2023-11-13T21:53:42.791362",
    "startedAt": "2023-11-13T21:53:42.020393",
    "docker": null,
    "cuda": null,
    "args": [
        "--batch_size=16",
        "--epochs=10",
        "--learning_rate=0.1",
        "--optimiser=Adagrad"
    ],
    "state": "running",
    "program": "/home/mihai/Documents/Personal/Facultate/Master Anul 1/Advanced topics in neural networks/Seminar/Lab05/Solution/main.py",
    "codePathLocal": "main.py",
    "codePath": "Lab05/Solution/main.py",
    "git": {
        "remote": "git@Github-Personal:MihaiBojescu/Advanced-Topics-in-Neural-Networks-2023.git",
        "commit": "8c28823149f34fa3bffa1f042cd381791a102a25"
    },
    "email": "bojescu.mihai@gmail.com",
    "root": "/home/mihai/Documents/Personal/Facultate/Master Anul 1/Advanced topics in neural networks/Seminar",
    "host": "mihais-framework",
    "username": "mihai",
    "executable": "/usr/bin/python",
    "cpu_count": 12,
    "cpu_count_logical": 16,
    "cpu_freq": {
        "current": 1323.6915,
        "min": 400.0,
        "max": 3400.0
    },
    "cpu_freq_per_core": [
        {
            "current": 1922.282,
            "min": 400.0,
            "max": 3400.0
        },
        {
            "current": 1775.441,
            "min": 400.0,
            "max": 3400.0
        },
        {
            "current": 1922.199,
            "min": 400.0,
            "max": 3400.0
        },
        {
            "current": 400.0,
            "min": 400.0,
            "max": 3400.0
        },
        {
            "current": 1046.777,
            "min": 400.0,
            "max": 3400.0
        },
        {
            "current": 1801.057,
            "min": 400.0,
            "max": 3400.0
        },
        {
            "current": 1818.066,
            "min": 400.0,
            "max": 3400.0
        },
        {
            "current": 1564.766,
            "min": 400.0,
            "max": 3400.0
        },
        {
            "current": 1337.151,
            "min": 400.0,
            "max": 3400.0
        },
        {
            "current": 1321.876,
            "min": 400.0,
            "max": 3400.0
        },
        {
            "current": 1336.461,
            "min": 400.0,
            "max": 3400.0
        },
        {
            "current": 1281.047,
            "min": 400.0,
            "max": 3400.0
        },
        {
            "current": 1388.997,
            "min": 400.0,
            "max": 3400.0
        },
        {
            "current": 1397.755,
            "min": 400.0,
            "max": 3400.0
        },
        {
            "current": 1384.188,
            "min": 400.0,
            "max": 3400.0
        },
        {
            "current": 1156.118,
            "min": 400.0,
            "max": 3400.0
        }
    ],
    "disk": {
        "/": {
            "total": 931.010440826416,
            "used": 577.5412940979004
        }
    },
    "memory": {
        "total": 31.0640869140625
    }
}
